airflow/providers/apache/iceberg/__init__.py
airflow/providers/apache/iceberg/get_provider_info.py
airflow/providers/apache/iceberg/version_compat.py
airflow/providers/apache/iceberg/hooks/__init__.py
airflow/providers/apache/iceberg/hooks/iceberg.py
apache_airflow_providers_apache_iceberg-1.4.1.dist-info/entry_points.txt
apache_airflow_providers_apache_iceberg-1.4.1.dist-info/licenses/LICENSE
apache_airflow_providers_apache_iceberg-1.4.1.dist-info/licenses/NOTICE
apache_airflow_providers_apache_iceberg-1.4.1.dist-info/WHEEL
apache_airflow_providers_apache_iceberg-1.4.1.dist-info/METADATA
apache_airflow_providers_apache_iceberg-1.4.1.dist-info/RECORD
